qtpandas-1.0.3-py3.5-nspkg.pth
qtpandas/compat.py
qtpandas/encoding.py
qtpandas/excepthook.py
qtpandas/utils.py
qtpandas/_lib/magic/libgcc_s_dw2-1.dll
qtpandas/_lib/magic/libmagic-1.dll
qtpandas/_lib/magic/libregex-1.dll
qtpandas/_lib/magic/magic1.dll
qtpandas/_lib/magic/zlib1.dll
qtpandas/_lib/magic/db/magic.mgc
qtpandas/i18n/de.qm
qtpandas/models/ColumnDtypeModel.py
qtpandas/models/DataFrameModel.py
qtpandas/models/DataFrameModelManager.py
qtpandas/models/DataSearch.py
qtpandas/models/ProgressThread.py
qtpandas/models/SupportedDtypes.py
qtpandas/models/__init__.py
qtpandas/models/mime.py
qtpandas/ui/__init__.py
qtpandas/ui/fallback/__init__.py
qtpandas/ui/fallback/easygui/__init__.py
qtpandas/ui/fallback/easygui/easygui.py
qtpandas/ui/fallback/easygui/boxes/__init__.py
qtpandas/ui/fallback/easygui/boxes/about.py
qtpandas/ui/fallback/easygui/boxes/base_boxes.py
qtpandas/ui/fallback/easygui/boxes/derived_boxes.py
qtpandas/ui/fallback/easygui/boxes/egstore.py
qtpandas/ui/fallback/easygui/boxes/state.py
qtpandas/ui/fallback/easygui/boxes/text_box.py
qtpandas/ui/fallback/easygui/boxes/updatable_text_box.py
qtpandas/ui/fallback/easygui/boxes/utils.py
qtpandas/views/BigIntSpinbox.py
qtpandas/views/CSVDialogs.py
qtpandas/views/CustomDelegates.py
qtpandas/views/DataTableView.py
qtpandas/views/EditDialogs.py
qtpandas/views/MultiFileDialogs.py
qtpandas/views/OverlayProgressView.py
qtpandas/views/__init__.py
qtpandas/views/_ui/__init__.py
qtpandas/views/_ui/icons_rc.py
qtpandas-1.0.3.dist-info/DESCRIPTION.rst
qtpandas-1.0.3.dist-info/METADATA
qtpandas-1.0.3.dist-info/RECORD
qtpandas-1.0.3.dist-info/WHEEL
qtpandas-1.0.3.dist-info/metadata.json
qtpandas-1.0.3.dist-info/namespace_packages.txt
qtpandas-1.0.3.dist-info/top_level.txt
