Metadata-Version: 2.0
Name: qtpandas
Version: 1.0.3
Summary: Utilities to use pandas (the data analysis / manipulation
Requires-Dist: easygui
Requires-Dist: pandas (==0.17.1)
Requires-Dist: pytest
Requires-Dist: pytest-cov
Requires-Dist: pytest-qt (==1.2.2)
Requires-Dist: python-magic (==0.4.6)
Provides-Extra: testing
Requires-Dist: easygui; extra == 'testing'
Requires-Dist: pandas (==0.17.1); extra == 'testing'
Requires-Dist: pyside; extra == 'testing'
Requires-Dist: pytest; extra == 'testing'
Requires-Dist: pytest-cov; extra == 'testing'
Requires-Dist: pytest-qt; extra == 'testing'
Requires-Dist: python-magic (==0.4.6); extra == 'testing'
